objectdict.py
objectdict-1.0.3.data/data/requirements.txt
objectdict-1.0.3.dist-info/METADATA
objectdict-1.0.3.dist-info/WHEEL
objectdict-1.0.3.dist-info/top_level.txt
objectdict-1.0.3.dist-info/RECORD
