Metadata-Version: 2.1
Name: objectdict
Version: 1.0.3
Summary: objectdict
Home-page: https://github.com/xzregg/pyobjectdict
Author: xzregg
Author-email: xzregg@gmail.com
Classifier: Programming Language :: Python :: 2
Classifier: License :: OSI Approved :: MIT License
Classifier: Operating System :: OS Independent
Requires-Python: >=2.7
